{
  "media_catalog": {
    "id": "e5a5e2e245544543e5a5e2e245544543",
    "external_id": "game:76888",
    "type": "game",
    "title_main": "Bayonetta 3",
    "source": "igdb",
    "created_at": "",
    "updated_at": "",
    "blocked_at": null
  },
  "media_relations": [
    {
      "media_external_id": "game:76888",
      "related_media_external_id": "game:2135",
      "relation_type": "PREQUEL",
      "type_label": "Prequel",
      "title": "Bayonetta 2",
      "cover": "https://images.igdb.com/igdb/image/upload/t_1080p/cob9e9.jpg"
    },
    {
      "media_external_id": "game:76888",
      "related_media_external_id": "game:228528",
      "relation_type": "SEQUEL",
      "type_label": "Sequel",
      "title": "Bayonetta Origins: Cereza and the Lost Demon",
      "cover": "https://images.igdb.com/igdb/image/upload/t_cover_big/co5vch.jpg"
    }
  ],
  "characters": [],
  "media_authors": [],
  "saga_groups": {},
  "saga_name": "Bayonetta"
}