{
  "media_catalog": {
    "id": "b098337ac2f3821fb098337ac2f3821f",
    "external_id": "game:8986",
    "parent_id": null,
    "type": "game",
    "format": "GAME",
    "source": "igdb",
    "title_main": "The Legend of Heroes: Trails in the Sky",
    "title_romaji": null,
    "title_native": "Eiyū Densetsu Sora no Kiseki",
    "synopsis": "The Legend of Heroes: Trails in the Sky is the first installment in the main Trails series, serving as the beginning to the Liberl arc and the series as a whole. The game follows protagonists Estelle Bright and her adopted brother Joshua, who journey through the country of Liberl to train to become senior Bracers, members of a non-government multinational organization that acts to keep the peace and protect civilians.\n\nNihon Falcom comes a series of RPGs telling a legend of adventure, political intrigue, and mystery, with a tale of growing up at the core. With a mix of turn-based and strategy combat, battles will cause unique builds and plans to handle many different situations and allow for different play styles. Wonderfully detailed characters abound, even to the smallest NPC, and the player will find themself taking the world in at every turn. Trails in the Sky sets a new standard for making an enjoyable and immersive RPG.",
    "cover_url": "https://images.igdb.com/igdb/image/upload/t_1080p/co7ybm.jpg",
    "banners_csv": "https://images.igdb.com/igdb/image/upload/t_1080p/scoobx.jpg",
    "release_year": 2004,
    "release_month": 6,
    "release_day": 24,
    "time_length": null,
    "status": null,
    "score_global": 8.6,
    "favorites_count": null,
    "ratings_count": null,
    "total_count": null,
    "total_count_2": null,
    "genres_csv": "Role-playing (RPG)",
    "genres_tag_csv": null,
    "platforms_csv": "PC (Microsoft Windows),PlayStation Portable",
    "shop_links_csv": null,
    "companies_cache_csv": "Nihon Falcom,XSEED Games,Ghostlight Ltd.,Marvelous USA, Inc.",
    "authors_csv": null,
    "last_synced_at": null,
    "sync_failed_count": null,
    "last_sync_error": null,
    "created_at": "2026-07-05T21:53:16.567Z",
    "updated_at": "2026-07-07T15:42:25.776095800+00:00"
  },
  "media_relations": [
    {
      "media_external_id": "game:8986",
      "related_media_external_id": "game:136287",
      "relation_type": "REMAKE",
      "type_label": "Remake",
      "title": "The Legend of Heroes: Sora no Kiseki FC Evolution",
      "cover": "https://images.igdb.com/igdb/image/upload/t_cover_big/co74e9.jpg"
    },
    {
      "media_external_id": "game:8986",
      "related_media_external_id": "game:136859",
      "relation_type": "REMASTER",
      "type_label": "Remaster",
      "title": "The Legend of Heroes: Sora no Kiseki FC Kai - HD",
      "cover": "https://images.igdb.com/igdb/image/upload/t_cover_big/co74ec.jpg"
    },
    {
      "media_external_id": "game:8986",
      "related_media_external_id": "game:314936",
      "relation_type": "REMAKE",
      "type_label": "Remake",
      "title": "Trails in the Sky 1st Chapter",
      "cover": "https://images.igdb.com/igdb/image/upload/t_cover_big/co96kj.jpg"
    },
    {
      "media_external_id": "game:8986",
      "related_media_external_id": "game:16665",
      "relation_type": "SEQUEL",
      "type_label": "Sequel",
      "title": "The Legend of Heroes: Trails in the Sky SC",
      "cover": "https://images.igdb.com/igdb/image/upload/t_cover_big/co74em.jpg"
    },
    {
      "media_external_id": "game:16665",
      "related_media_external_id": "game:8986",
      "relation_type": "PREQUEL",
      "type_label": "Prequel",
      "title": "The Legend of Heroes: Trails in the Sky",
      "cover": "https://images.igdb.com/igdb/image/upload/t_1080p/co7ybm.jpg"
    },
    {
      "media_external_id": "game:16665",
      "related_media_external_id": "game:28101",
      "relation_type": "SEQUEL",
      "type_label": "Sequel",
      "title": "The Legend of Heroes: Trails in the Sky the 3rd",
      "cover": "https://images.igdb.com/igdb/image/upload/t_cover_big/co23da.jpg"
    },
    {
      "media_external_id": "game:28101",
      "related_media_external_id": "game:16665",
      "relation_type": "PREQUEL",
      "type_label": "Prequel",
      "title": "The Legend of Heroes: Trails in the Sky SC",
      "cover": "https://images.igdb.com/igdb/image/upload/t_cover_big/co74em.jpg"
    },
    {
      "media_external_id": "game:28101",
      "related_media_external_id": "game:192133",
      "relation_type": "SEQUEL",
      "type_label": "Sequel",
      "title": "The Legend of Heroes: Zero no Kiseki",
      "cover": "https://images.igdb.com/igdb/image/upload/t_cover_big/co7527.jpg"
    },
    {
      "media_external_id": "game:192133",
      "related_media_external_id": "game:28101",
      "relation_type": "PREQUEL",
      "type_label": "Prequel",
      "title": "The Legend of Heroes: Trails in the Sky the 3rd",
      "cover": "https://images.igdb.com/igdb/image/upload/t_cover_big/co23da.jpg"
    },
    {
      "media_external_id": "game:192133",
      "related_media_external_id": "game:284036",
      "relation_type": "SEQUEL",
      "type_label": "Sequel",
      "title": "The Legend of Heroes: Ao no Kiseki",
      "cover": "https://images.igdb.com/igdb/image/upload/t_cover_big/co7oqe.jpg"
    },
    {
      "media_external_id": "game:284036",
      "related_media_external_id": "game:192133",
      "relation_type": "PREQUEL",
      "type_label": "Prequel",
      "title": "The Legend of Heroes: Zero no Kiseki",
      "cover": "https://images.igdb.com/igdb/image/upload/t_cover_big/co7527.jpg"
    },
    {
      "media_external_id": "game:284036",
      "related_media_external_id": "game:13557",
      "relation_type": "SEQUEL",
      "type_label": "Sequel",
      "title": "The Legend of Heroes: Trails of Cold Steel",
      "cover": "https://images.igdb.com/igdb/image/upload/t_cover_big/co44ma.jpg"
    },
    {
      "media_external_id": "game:13557",
      "related_media_external_id": "game:284036",
      "relation_type": "PREQUEL",
      "type_label": "Prequel",
      "title": "The Legend of Heroes: Ao no Kiseki",
      "cover": "https://images.igdb.com/igdb/image/upload/t_cover_big/co7oqe.jpg"
    },
    {
      "media_external_id": "game:13557",
      "related_media_external_id": "game:13558",
      "relation_type": "SEQUEL",
      "type_label": "Sequel",
      "title": "The Legend of Heroes: Trails of Cold Steel II",
      "cover": "https://images.igdb.com/igdb/image/upload/t_cover_big/co44mb.jpg"
    },
    {
      "media_external_id": "game:13558",
      "related_media_external_id": "game:13557",
      "relation_type": "PREQUEL",
      "type_label": "Prequel",
      "title": "The Legend of Heroes: Trails of Cold Steel",
      "cover": "https://images.igdb.com/igdb/image/upload/t_cover_big/co44ma.jpg"
    },
    {
      "media_external_id": "game:13558",
      "related_media_external_id": "game:26564",
      "relation_type": "SEQUEL",
      "type_label": "Sequel",
      "title": "The Legend of Heroes: Trails of Cold Steel III",
      "cover": "https://images.igdb.com/igdb/image/upload/t_cover_big/cobb5w.jpg"
    },
    {
      "media_external_id": "game:26564",
      "related_media_external_id": "game:13558",
      "relation_type": "PREQUEL",
      "type_label": "Prequel",
      "title": "The Legend of Heroes: Trails of Cold Steel II",
      "cover": "https://images.igdb.com/igdb/image/upload/t_cover_big/co44mb.jpg"
    },
    {
      "media_external_id": "game:26564",
      "related_media_external_id": "game:78115",
      "relation_type": "SEQUEL",
      "type_label": "Sequel",
      "title": "The Legend of Heroes: Trails of Cold Steel IV",
      "cover": "https://images.igdb.com/igdb/image/upload/t_cover_big/co31wc.jpg"
    },
    {
      "media_external_id": "game:78115",
      "related_media_external_id": "game:26564",
      "relation_type": "PREQUEL",
      "type_label": "Prequel",
      "title": "The Legend of Heroes: Trails of Cold Steel III",
      "cover": "https://images.igdb.com/igdb/image/upload/t_cover_big/cobb5w.jpg"
    },
    {
      "media_external_id": "game:78115",
      "related_media_external_id": "game:136673",
      "relation_type": "SEQUEL",
      "type_label": "Sequel",
      "title": "The Legend of Heroes: Trails into Reverie",
      "cover": "https://images.igdb.com/igdb/image/upload/t_cover_big/co3bb2.jpg"
    },
    {
      "media_external_id": "game:136673",
      "related_media_external_id": "game:78115",
      "relation_type": "PREQUEL",
      "type_label": "Prequel",
      "title": "The Legend of Heroes: Trails of Cold Steel IV",
      "cover": "https://images.igdb.com/igdb/image/upload/t_cover_big/co31wc.jpg"
    },
    {
      "media_external_id": "game:136673",
      "related_media_external_id": "game:141833",
      "relation_type": "SEQUEL",
      "type_label": "Sequel",
      "title": "The Legend of Heroes: Trails Through Daybreak",
      "cover": "https://images.igdb.com/igdb/image/upload/t_cover_big/cobjpy.jpg"
    },
    {
      "media_external_id": "game:141833",
      "related_media_external_id": "game:136673",
      "relation_type": "PREQUEL",
      "type_label": "Prequel",
      "title": "The Legend of Heroes: Trails into Reverie",
      "cover": "https://images.igdb.com/igdb/image/upload/t_cover_big/co3bb2.jpg"
    },
    {
      "media_external_id": "game:141833",
      "related_media_external_id": "game:185864",
      "relation_type": "SEQUEL",
      "type_label": "Sequel",
      "title": "The Legend of Heroes: Trails Through Daybreak II",
      "cover": "https://images.igdb.com/igdb/image/upload/t_cover_big/co8l3f.jpg"
    },
    {
      "media_external_id": "game:185864",
      "related_media_external_id": "game:141833",
      "relation_type": "PREQUEL",
      "type_label": "Prequel",
      "title": "The Legend of Heroes: Trails Through Daybreak",
      "cover": "https://images.igdb.com/igdb/image/upload/t_cover_big/cobjpy.jpg"
    },
    {
      "media_external_id": "game:185864",
      "related_media_external_id": "game:280573",
      "relation_type": "SEQUEL",
      "type_label": "Sequel",
      "title": "The Legend of Heroes: Trails Beyond the Horizon",
      "cover": "https://images.igdb.com/igdb/image/upload/t_cover_big/cobjgs.jpg"
    },
    {
      "media_external_id": "game:280573",
      "related_media_external_id": "game:185864",
      "relation_type": "PREQUEL",
      "type_label": "Prequel",
      "title": "The Legend of Heroes: Trails Through Daybreak II",
      "cover": "https://images.igdb.com/igdb/image/upload/t_cover_big/co8l3f.jpg"
    }
  ],
  "characters": [],
  "media_authors": [],
  "saga_groups": {}
}